Workbook

Sheet VAT_Return
A1: VATflow | United Fintec — VAT Return Summary
A2: Making Tax Digital · All Schemes · All 9 Boxes · HMRC API Ready
A3: Business / Company Name: | C3: [Enter Business Name]
A4: VAT Registration Number (VRN): | C4: [e.g. GB123456789]
A5: VAT Accounting Scheme: | C5: Flat Rate
A6: Flat Rate % (if applicable): | C6: 0.165
A7: VAT Period Start:
A8: VAT Period End:
A9: Submission Due Date:
A11: 9-Box VAT Return — Auto-populated from Sales & Expenses tabs
A12: Box | B12: Description | C12: Amount (£) | D12: Notes / Source | E12: Status
A13: 1 | B13: VAT due on sales and other outputs | C13: =Sales!G4 | D13: From Sales sheet | E13: ✔ Linked
A14: 2 | B14: VAT due on EC acquisitions (NI only) | C14: =Expenses!G4 | D14: NI traders only | E14: ✔ Linked
A15: 3 | B15: Total VAT due (Box 1 + Box 2) | C15: =C13+C14 | D15: AUTO-CALCULATED | E15: AUTO
A16: 4 | B16: VAT reclaimed on purchases and inputs | C16: =Expenses!F4 | D16: From Expenses sheet | E16: ✔ Linked
A17: 5 | B17: Net VAT to be paid or reclaimed | C17: =C15-C16 | D17: AUTO-CALCULATED | E17: AUTO
A18: 6 | B18: Total value of sales (excluding VAT) | C18: =Sales!D4 | D18: From Sales sheet | E18: ✔ Linked
A19: 7 | B19: Total value of purchases (excl. VAT) | C19: =Expenses!D4 | D19: From Expenses | E19: ✔ Linked
A20: 8 | B20: Goods to EC member states (excl. VAT) | C20: 0 | D20: Enter if applicable | E20: ✔ Linked
A21: 9 | B21: Goods from EC member states (NI only) | C21: 0 | D21: NI traders only | E21: ✔ Linked
A23: COLOUR KEY: Blue = Input cells | Black bold = Auto-calculated | Yellow = Required input | Green = Key result
A24: Instructions: 1) Fill business details 2) Enter sales in Sales tab 3) Enter expenses in Expenses tab 4) Upload to VATflow app at vatflow.co.uk

Sheet Sales
A1: SALES — VATflow by United Fintec
A2: Business: | C2: =VAT_Return!C3 | G2: Period end: =VAT_Return!C8
A3: ℹ Standard scheme: VAT Amount = Net × Rate | Flat Rate: Box 1 = Total (incl VAT) × FRS% | Enter all sales invoices below
A4: TOTALS | D4: =SUM(D6:D205) | F4: =SUM(F6:F205) | G4: =SUM(G6:G205)
A5: INVOICE NO. | B5: CUSTOMER NAME | C5: DATE | D5: NET AMOUNT | E5: VAT RATE % | F5: VAT AMOUNT | G5: TOTAL AMOUNT | H5: CATEGORY
E6: 0.2 | F6: =IF(D6="",0,D6*E6) | G6: =IF(D6="",0,D6+F6)
E7: 0.2 | F7: =IF(D7="",0,D7*E7) | G7: =IF(D7="",0,D7+F7)
E8: 0.2 | F8: =IF(D8="",0,D8*E8) | G8: =IF(D8="",0,D8+F8)
E9: 0.2 | F9: =IF(D9="",0,D9*E9) | G9: =IF(D9="",0,D9+F9)
E10: 0.2 | F10: =IF(D10="",0,D10*E10) | G10: =IF(D10="",0,D10+F10)
E11: 0.2 | F11: =IF(D11="",0,D11*E11) | G11: =IF(D11="",0,D11+F11)
E12: 0.2 | F12: =IF(D12="",0,D12*E12) | G12: =IF(D12="",0,D12+F12)
E13: 0.2 | F13: =IF(D13="",0,D13*E13) | G13: =IF(D13="",0,D13+F13)
E14: 0.2 | F14: =IF(D14="",0,D14*E14) | G14: =IF(D14="",0,D14+F14)
E15: 0.2 | F15: =IF(D15="",0,D15*E15) | G15: =IF(D15="",0,D15+F15)
E16: 0.2 | F16: =IF(D16="",0,D16*E16) | G16: =IF(D16="",0,D16+F16)
E17: 0.2 | F17: =IF(D17="",0,D17*E17) | G17: =IF(D17="",0,D17+F17)
... E205: 0.2 | F205: =IF(D205="",0,D205*E205) | G205: =IF(D205="",0,D205+F205)

Sheet Expenses
A1: EXPENSES — VATflow by United Fintec
A2: FLAT RATE SCHEME: You normally CANNOT reclaim input VAT. Exception: single capital goods purchase of £2,000+ (incl. VAT). See HMRC VAT Notice 733.
A4: TOTALS | D4: =SUM(D6:D205) | F4: =SUMIF(H6:H205,"Claimable",F6:F205) | G4: =SUM(G6:G205)
A5: RECEIPT/INV NO. | B5: SUPPLIER NAME | C5: DATE | D5: NET AMOUNT | E5: VAT RATE % | F5: VAT AMOUNT | G5: TOTAL AMOUNT | H5: EXPENSE TYPE
E6: 0.2 | F6: =IF(D6="",0,D6*E6) | G6: =IF(D6="",0,D6+F6) | H6: Not claimable
E7: 0.2 | F7: =IF(D7="",0,D7*E7) | G7: =IF(D7="",0,D7+F7) | H7: Not claimable
E8: 0.2 | F8: =IF(D8="",0,D8*E8) | G8: =IF(D8="",0,D8+F8) | H8: Not claimable
E9: 0.2 | F9: =IF(D9="",0,D9*E9) | G9: =IF(D9="",0,D9+F9) | H9: Not claimable
E10: 0.2 | F10: =IF(D10="",0,D10*E10) | G10: =IF(D10="",0,D10+F10) | H10: Not claimable
E11: 0.2 | F11: =IF(D11="",0,D11*E11) | G11: =IF(D11="",0,D11+F11) | H11: Not claimable
E12: 0.2 | F12: =IF(D12="",0,D12*E12) | G12: =IF(D12="",0,D12+F12) | H12: Not claimable
E13: 0.2 | F13: =IF(D13="",0,D13*E13) | G13: =IF(D13="",0,D13+F13) | H13: Not claimable
E14: 0.2 | F14: =IF(D14="",0,D14*E14) | G14: =IF(D14="",0,D14+F14) | H14: Not claimable
E15: 0.2 | F15: =IF(D15="",0,D15*E15) | G15: =IF(D15="",0,D15+F15) | H15: Not claimable
E16: 0.2 | F16: =IF(D16="",0,D16*E16) | G16: =IF(D16="",0,D16+F16) | H16: Not claimable
E17: 0.2 | F17: =IF(D17="",0,D17*E17) | G17: =IF(D17="",0,D17+F17) | H17: Not claimable
... E205: 0.2 | F205: =IF(D205="",0,D205*E205) | G205: =IF(D205="",0,D205+F205) | H205: Not claimable

Sheet FlatRate_Calc
A1: Flat Rate Scheme Calculator — HMRC VAT Notice 733
A3: Total Sales incl. VAT (Gross turnover) | B3: =VAT_Return!C18*1.2
A4: Flat Rate Percentage | B4: =VAT_Return!C6
A5: VAT Payable (Box 1) = Gross × FRS% | B5: =B3*B4
A6: VAT Charged to Customers (20% of net) | B6: =VAT_Return!C18*0.2
A7: FRS Saving vs Standard Rate | B7: =B6-B5
A9: Common FRS Sector Percentages (HMRC 2025)
A10: Accountancy / bookkeeping | B10: 14.5%
A11: IT & computer services | B11: 14.5%
A12: Management consultancy | B12: 14.0%
A13: Financial services | B13: 13.5%
A14: Legal services | B14: 14.5%
A15: Business services (general) | B15: 12.0%
A16: Catering | B16: 12.5%
A17: Retail – general | B17: 7.5%
A18: Transport & logistics | B18: 10.0%
A19: Healthcare | B19: 12.0%

Sheet Instructions
A1: VATflow — Excel Template Guide | United Fintec Limited | vatflow.co.uk
A3: STEP 1 | B3: Open VAT_Return tab → fill in Business Name, VRN, period dates, scheme. Select scheme from dropdown. For Flat Rate, enter your sector percentage.
A4: STEP 2 | B4: Go to Sales tab → enter each invoice: Invoice No, Customer, Date, Net Amount. VAT Amount & Total calculate automatically. Select VAT rate from dropdown (0%, 5%, 20%).
A5: STEP 3 | B5: Go to Expenses tab → enter each purchase. For Flat Rate Scheme, set Expense Type = 'Not claimable' UNLESS it is a capital goods purchase of £2,000+ (incl. VAT).
A6: STEP 4 | B6: Check FlatRate_Calc tab if on FRS — automatically shows Box 1 VAT payable and your saving vs standard rate.
A7: STEP 5 | B7: Return to VAT_Return → all 9 boxes auto-populate from Sales and Expenses. Verify the figures look correct.
A8: STEP 6 | B8: Save the completed file. Upload to VATflow at vatflow.co.uk → Import Data → Upload Excel Template. The app reads your 9-box values and submits to HMRC via the MTD API.
A9: STEP 7 | B9: Keep this file for 6 years (MTD digital records requirement). Do NOT manually retype figures between systems — this file IS your digital link under SI 2018/261.
A11: ⚠ CRITICAL: Do NOT copy-paste values between sheets manually — this breaks the digital link required by HMRC MTD (SI 2018/261) and may invalidate your return.
A12: VATflow by United Fintec Limited · vatflow.co.uk · support@unitedfintec.com · © 2025 United Fintec Limited
